refaci/__init__.py
refaci/__main__.py
refaci/gather.py
refaci/refactor.py
refaci-1.0.0.dist-info/entry_points.txt
refaci-1.0.0.dist-info/LICENSE
refaci-1.0.0.dist-info/WHEEL
refaci-1.0.0.dist-info/METADATA
refaci-1.0.0.dist-info/RECORD
