Metadata-Version: 2.1
Name: refaci
Version: 1.0.0
Summary: 
Home-page: https://github.com/ovsyanka83/refaci
License: MIT
Author: Stanislav Zmiev
Author-email: szmiev2000@gmail.com
Requires-Python: >=3.10,<4.0
Classifier: License :: OSI Approved :: MIT License
Classifier: Programming Language :: Python :: 3
Classifier: Programming Language :: Python :: 3.10
Classifier: Programming Language :: Python :: 3.11
Requires-Dist: typer[all]
Requires-Dist: typing-extensions
Project-URL: Repository, https://github.com/ovsyanka83/refaci
